frankencircuits
