Metadata-Version: 1.1
Name: FrankenCircuits
Version: 0.1.1.ALPHA-
Summary: Plugin library for Circuits and Circuits.Web
Home-page: http://bitbucket.org/jgiorgi/frankencircuits
Author: Justin Giorgi
Author-email: justin@justingiorgi.com
License: GPLv3
Download-URL: http://bitbucket.org/jgiorgi/frankencircuits/downloads
Keywords: plugin,library,circuits,framework,circuits.web,web
Platform: UNKNOWN
Classifier: Development Status :: 3 - Alpha
Classifier: License :: OSI Approved :: GNU General Public License v3 or later (GPLv3+)
Classifier: Natural Language :: English
Classifier: Operating System :: OS Independent
Classifier: Programming Language :: Python :: 2.6
Classifier: Programming Language :: Python :: 2.7
Classifier: Topic :: Software Development :: Libraries
Requires: C
Requires: i
Requires: r
Requires: c
Requires: u
Requires: i
Requires: t
Requires: s
